labeler/__init__.py
labeler/admin.py
labeler/admin_auto.py
labeler/apps.py
labeler/forms.py
labeler/models.py
labeler/serializers.py
labeler/tests.py
labeler/trainer.py
labeler/urls.py
labeler/views.py
labeler/data/DSC_4621.jpg
labeler/data/HUNT0133.jpg
labeler/data/HUNT0726.jpg
labeler/data/HUNT1306.jpg
labeler/data/SUNP0254.jpg
labeler/fixtures/labeler_test_data.json
labeler/migrations/0001_initial.py
labeler/migrations/0002_image_file.py
labeler/migrations/0003_auto_20170803_2247.py
labeler/migrations/0004_auto_20170803_2308.py
labeler/migrations/0005_auto_20170804_0802.py
labeler/migrations/0006_auto_20170804_0923.py
labeler/migrations/0007_auto_20170821_1733.py
labeler/migrations/0008_auto_20170823_1618.py
labeler/migrations/0009_auto_20170824_1704.py
labeler/migrations/0010_auto_20170829_0758.py
labeler/migrations/__init__.py
labeler/templates/base.html
labeler/templates/labeler/form_file_upload.html
labeler/templates/labeler/index.html
labeler-0.0.1.data/data/share/labeler_docs/Makefile
labeler-0.0.1.data/data/share/labeler_docs/authors.rst
labeler-0.0.1.data/data/share/labeler_docs/changes.rst
labeler-0.0.1.data/data/share/labeler_docs/conf.py
labeler-0.0.1.data/data/share/labeler_docs/index.rst
labeler-0.0.1.data/data/share/labeler_docs/license.rst
labeler-0.0.1.data/data/share/labeler_docs/research.md
labeler-0.0.1.data/data/share/labeler_docs/_static/.gitignore
labeler-0.0.1.dist-info/DESCRIPTION.rst
labeler-0.0.1.dist-info/METADATA
labeler-0.0.1.dist-info/RECORD
labeler-0.0.1.dist-info/WHEEL
labeler-0.0.1.dist-info/entry_points.txt
labeler-0.0.1.dist-info/metadata.json
labeler-0.0.1.dist-info/top_level.txt
labeler_site/__init__.py
labeler_site/bot.py
labeler_site/image_info.py
labeler_site/settings.py
labeler_site/urls.py
labeler_site/wsgi.py
